{
  "$schema": "https://developer.microsoft.com/json-schemas/fabric/item/report/definition/visualContainer/2.8.0/schema.json",
  "name": "ff8eec40eab50fb31f4d",
  "position": {
    "x": 760.65878209361426,
    "y": 0,
    "z": 4000,
    "height": 360.65718116507571,
    "width": 519.67421104240452,
    "tabOrder": 3000
  },
  "visual": {
    "visualType": "clusteredColumnChart",
    "query": {
      "queryState": {
        "Category": {
          "projections": [
            {
              "field": {
                "Column": {
                  "Expression": {
                    "SourceRef": {
                      "Entity": "Fact_Listings"
                    }
                  },
                  "Property": "Khoảng đơn giá/m²"
                }
              },
              "queryRef": "Fact_Listings.Khoảng đơn giá/m²",
              "nativeQueryRef": "Khoảng đơn giá/m²",
              "active": true
            }
          ]
        },
        "Y": {
          "projections": [
            {
              "field": {
                "Measure": {
                  "Expression": {
                    "SourceRef": {
                      "Entity": "Fact_Listings"
                    }
                  },
                  "Property": "Số tin đăng"
                }
              },
              "queryRef": "Fact_Listings.Số tin đăng",
              "nativeQueryRef": "Số tin đăng"
            }
          ]
        }
      },
      "sortDefinition": {
        "sort": [
          {
            "field": {
              "Measure": {
                "Expression": {
                  "SourceRef": {
                    "Entity": "Fact_Listings"
                  }
                },
                "Property": "Số tin đăng"
              }
            },
            "direction": "Descending"
          }
        ],
        "isDefaultSort": true
      }
    },
    "objects": {
      "categoryAxis": [
        {
          "properties": {
            "titleText": {
              "expr": {
                "Literal": {
                  "Value": "'Khoảng đơn giá/m² (triệu đồng)'"
                }
              }
            },
            "titleFontFamily": {
              "expr": {
                "Literal": {
                  "Value": "'''Segoe UI Semibold'', wf_segoe-ui_semibold, helvetica, arial, sans-serif'"
                }
              }
            }
          }
        }
      ],
      "valueAxis": [
        {
          "properties": {
            "titleText": {
              "expr": {
                "Literal": {
                  "Value": "'Số lượng tin đăng'"
                }
              }
            },
            "titleFontFamily": {
              "expr": {
                "Literal": {
                  "Value": "'''Segoe UI Semibold'', wf_segoe-ui_semibold, helvetica, arial, sans-serif'"
                }
              }
            }
          }
        }
      ],
      "xAxisReferenceLine": [
        {
          "properties": {
            "show": {
              "expr": {
                "Literal": {
                  "Value": "true"
                }
              }
            },
            "displayName": {
              "expr": {
                "Literal": {
                  "Value": "'X-Axis Constant Line 1'"
                }
              }
            },
            "value": {
              "expr": {
                "Literal": {
                  "Value": "44.2D"
                }
              }
            },
            "lineColor": {
              "solid": {
                "color": {
                  "expr": {
                    "ThemeDataColor": {
                      "ColorId": 9,
                      "Percent": -0.5
                    }
                  }
                }
              }
            },
            "transparency": {
              "expr": {
                "Literal": {
                  "Value": "42D"
                }
              }
            }
          },
          "selector": {
            "id": "1"
          }
        }
      ],
      "labels": [
        {
          "properties": {
            "show": {
              "expr": {
                "Literal": {
                  "Value": "false"
                }
              }
            }
          }
        }
      ]
    },
    "visualContainerObjects": {
      "title": [
        {
          "properties": {
            "text": {
              "expr": {
                "Literal": {
                  "Value": "'Phân phối đơn giá/m² và ngưỡng rẻ bất thường'"
                }
              }
            },
            "fontFamily": {
              "expr": {
                "Literal": {
                  "Value": "'''Segoe UI Semibold'', wf_segoe-ui_semibold, helvetica, arial, sans-serif'"
                }
              }
            }
          }
        }
      ]
    },
    "drillFilterOtherVisuals": true
  },
  "filterConfig": {
    "filters": [
      {
        "name": "9d957fc6fa57c70b7cf0",
        "field": {
          "Column": {
            "Expression": {
              "SourceRef": {
                "Entity": "Fact_Listings"
              }
            },
            "Property": "Khoảng đơn giá/m²"
          }
        },
        "type": "Advanced",
        "filter": {
          "Version": 2,
          "From": [
            {
              "Name": "f",
              "Entity": "Fact_Listings",
              "Type": 0
            }
          ],
          "Where": [
            {
              "Condition": {
                "Comparison": {
                  "ComparisonKind": 3,
                  "Left": {
                    "Column": {
                      "Expression": {
                        "SourceRef": {
                          "Source": "f"
                        }
                      },
                      "Property": "Khoảng đơn giá/m²"
                    }
                  },
                  "Right": {
                    "Literal": {
                      "Value": "600L"
                    }
                  }
                }
              }
            }
          ]
        }
      },
      {
        "name": "2aa900ffbaa3dbda2a7f",
        "field": {
          "Measure": {
            "Expression": {
              "SourceRef": {
                "Entity": "Fact_Listings"
              }
            },
            "Property": "Số tin đăng"
          }
        },
        "type": "Advanced"
      }
    ]
  }
}